MANIFEST.in
setup.cfg
setup.py
cmd/metallum
metallum/__init__.py
metallum/metallum.py
metallum/metrolyrics.py
metallum.egg-info/PKG-INFO
metallum.egg-info/SOURCES.txt
metallum.egg-info/dependency_links.txt
metallum.egg-info/not-zip-safe
metallum.egg-info/requires.txt
metallum.egg-info/top_level.txt
test/test.py