Metadata-Version: 1.2
Name: metallum
Version: 0.5
Summary: Console current lyrics visualizer
Home-page: http://yeisoncardona.com
Author: 
Author-email: 
Maintainer: Yeison Cardona
Maintainer-email: yeisoneng@gmail.com
License: GPLv3
Keywords: Spotify,lyrics,metallum
Platform: UNKNOWN
